easyaudiostream/__init__.py
easyaudiostream/__main__.py
easyaudiostream/_capabilities.py
easyaudiostream/_version.py
easyaudiostream/audio.py
easyaudiostream/mic.py
easyaudiostream-0.0.1.dist-info/METADATA
easyaudiostream-0.0.1.dist-info/WHEEL
easyaudiostream-0.0.1.dist-info/licenses/LICENSE
easyaudiostream-0.0.1.dist-info/RECORD
