Metadata-Version: 2.4
Name: easyaudiostream
Version: 0.0.1
Summary: Simple playback for intermittent audio byte streams in Python.
Project-URL: Homepage, https://github.com/zhudotexe/easyaudiostream
Project-URL: Bug Tracker, https://github.com/zhudotexe/easyaudiostream/issues
Author-email: Andrew Zhu <andrew@zhu.codes>
License: MIT License
License-File: LICENSE
Classifier: Intended Audience :: Developers
Classifier: License :: OSI Approved :: MIT License
Classifier: Operating System :: OS Independent
Classifier: Programming Language :: Python :: 3
Classifier: Topic :: Multimedia :: Sound/Audio :: Players
Requires-Python: >=3.10
Requires-Dist: pydub<1.0.0,>=0.25.0
Provides-Extra: pyaudio
Requires-Dist: pyaudio<1.0.0,>=0.2.0; extra == 'pyaudio'
